swagger_conformance-0.2.5.dist-info/DESCRIPTION.rst
swagger_conformance-0.2.5.dist-info/METADATA
swagger_conformance-0.2.5.dist-info/RECORD
swagger_conformance-0.2.5.dist-info/WHEEL
swagger_conformance-0.2.5.dist-info/metadata.json
swagger_conformance-0.2.5.dist-info/top_level.txt
swaggerconformance/__init__.py
swaggerconformance/__main__.py
swaggerconformance/_basictests.py
swaggerconformance/client.py
swaggerconformance/codec.py
swaggerconformance/main.py
swaggerconformance/response.py
swaggerconformance/strategies.py
swaggerconformance/apitemplates/__init__.py
swaggerconformance/apitemplates/_apitemplate.py
swaggerconformance/apitemplates/_operationtemplate.py
swaggerconformance/apitemplates/_parametertemplate.py
swaggerconformance/apitemplates/_swaggerdefinition.py
swaggerconformance/apitemplates/_swaggerparameter.py
swaggerconformance/schema/__init__.py
swaggerconformance/schema/_api.py
swaggerconformance/schema/_operation.py
swaggerconformance/schema/_parameter.py
swaggerconformance/schema/_primitive.py
swaggerconformance/strategies/__init__.py
swaggerconformance/strategies/_strategyfactory.py
swaggerconformance/strategies/basestrategies.py
swaggerconformance/strategies/primitivestrategies.py
swaggerconformance/template/__init__.py
swaggerconformance/template/apitemplate.py
swaggerconformance/template/operationtemplate.py
swaggerconformance/template/parametertemplate.py
swaggerconformance/template/strategies.py
swaggerconformance/template/swaggerparameter.py
swaggerconformance/template/valuetemplatefactory.py
swaggerconformance/template/valuetemplates.py
swaggerconformance/valuetemplates/__init__.py
swaggerconformance/valuetemplates/_valuetemplatefactory.py
swaggerconformance/valuetemplates/_valuetemplates.py
swaggerconformance/valuetemplates/valuetemplatefactory.py
swaggerconformance/valuetemplates/valuetemplates.py
