Metadata-Version: 2.0
Name: swagger-conformance
Version: 0.2.5
Summary: Tool for testing whether your API conforms to its swagger specification
Home-page: https://github.com/olipratt/swagger-conformance
Author: Oli Pratt
Author-email: olipratt@users.noreply.github.com
License: MIT
Download-URL: https://github.com/olipratt/swagger-conformance/archive/0.2.5.tar.gz
Keywords: swagger,testing,OpenAPI,hypothesis
Platform: UNKNOWN
Classifier: Development Status :: 4 - Beta
Classifier: Intended Audience :: Developers
Classifier: License :: OSI Approved :: MIT License
Classifier: Operating System :: OS Independent
Classifier: Programming Language :: Python :: 3 :: Only
Classifier: Programming Language :: Python :: 3.4
Classifier: Programming Language :: Python :: 3.5
Classifier: Programming Language :: Python :: 3.6
Classifier: Topic :: Software Development :: Testing
Requires-Dist: hypothesis (>=3.4.2)
Requires-Dist: pyswagger (>=0.8.38)
Requires-Dist: requests (>=2.13.0)
